napari_psf_extractor/__init__.py
napari_psf_extractor/_tests/__init__.py
napari_psf_extractor/_tests/test_plotting.py
napari_psf_extractor/_tests/test_util.py
napari_psf_extractor/components/__init__.py
napari_psf_extractor/components/pcc.py
napari_psf_extractor/components/sliders.py
napari_psf_extractor/components/statusbar.py
napari_psf_extractor/extractor.py
napari_psf_extractor/features.py
napari_psf_extractor/napari.yaml
napari_psf_extractor/plotting.py
napari_psf_extractor/utils.py
napari_psf_extractor/widget.py
napari_psf_extractor-1.0.2.dist-info/LICENSE
napari_psf_extractor-1.0.2.dist-info/METADATA
napari_psf_extractor-1.0.2.dist-info/WHEEL
napari_psf_extractor-1.0.2.dist-info/RECORD
