Metadata-Version: 2.1
Name: napari-psf-extractor
Version: 1.0.2
Summary: A simple plugin to extract precise models of the Point Spread Functions of images
Author: Alexandru Bolfa
Author-email: me@alexbolfa.com
Requires-Python: >=3.8,<4.0
Classifier: Framework :: napari
Classifier: Programming Language :: Python :: 3
Classifier: Programming Language :: Python :: 3.8
Classifier: Programming Language :: Python :: 3.9
Classifier: Programming Language :: Python :: 3.10
Classifier: Programming Language :: Python :: 3.11
Classifier: Programming Language :: Python :: 3.12
Provides-Extra: testing
Requires-Dist: magicgui
Requires-Dist: matplotlib
Requires-Dist: numpy
Requires-Dist: opencv-python
Requires-Dist: qtpy
Requires-Dist: superqt
Requires-Dist: trackpy
